mopac/__init__.py
mopac/mopac.py
mopac-0.9.1.dist-info/LICENSE
mopac-0.9.1.dist-info/METADATA
mopac-0.9.1.dist-info/WHEEL
mopac-0.9.1.dist-info/entry_points.txt
mopac-0.9.1.dist-info/top_level.txt
mopac-0.9.1.dist-info/RECORD
